LICENSE
MANIFEST.in
README.md
pyproject.toml
setup.cfg
setup.py
pick_git/__init__.py
pick_git/command_line.py
pick_git/core.py
pick_git/helpers.py
pick_git/pg.py
pick_git.egg-info/PKG-INFO
pick_git.egg-info/SOURCES.txt
pick_git.egg-info/dependency_links.txt
pick_git.egg-info/entry_points.txt
pick_git.egg-info/requires.txt
pick_git.egg-info/top_level.txt