Metadata-Version: 1.1
Name: pick-git
Version: 2.0.0
Summary: Use fzf to turbocharge your Git workflow
Home-page: https://github.com/kylebebak/pick-git
Author: kylebebak
Author-email: kylebebak@gmail.com
License: MIT
Download-URL: https://github.com/kylebebak/pick-git/tarball/2.0.0
Keywords: fzf git fuzzy select terminal productivity
Platform: UNKNOWN
Classifier: Intended Audience :: Developers
Classifier: License :: OSI Approved :: MIT License
Classifier: Programming Language :: Python
